browsing_history/__init__.py
browsing_history/core.py
browsing_history/models.py
browsing_history/schemas.py
tns_browsing_history-0.1.0.dist-info/licenses/LICENSE
tns_browsing_history-0.1.0.dist-info/METADATA
tns_browsing_history-0.1.0.dist-info/WHEEL
tns_browsing_history-0.1.0.dist-info/top_level.txt
tns_browsing_history-0.1.0.dist-info/RECORD
